tinytimmy/202306-divvy-tripdata.csv
tinytimmy/__init__.py
tinytimmy/config_parser.py
tinytimmy/data_quality.py
tinytimmy/tinytim.py
tinytimmy-0.1.4.dist-info/LICENSE
tinytimmy-0.1.4.dist-info/METADATA
tinytimmy-0.1.4.dist-info/WHEEL
tinytimmy-0.1.4.dist-info/RECORD
