Metadata-Version: 2.1
Name: tinytimmy
Version: 0.1.4
Summary: A simple and easy to use Data Quality (DQ) tool built with Python.
Author: Daniel Beach
Author-email: dancrystalbeach@gmail.com
Requires-Python: >=3.9,<4.0
Classifier: Programming Language :: Python :: 3
Classifier: Programming Language :: Python :: 3.9
Classifier: Programming Language :: Python :: 3.10
Classifier: Programming Language :: Python :: 3.11
Requires-Dist: loguru (>=0.7.0,<0.8.0)
Requires-Dist: pandas (==2.0.3)
Requires-Dist: polars (==0.18.13)
Requires-Dist: pyarrow (==12.0.1)
Requires-Dist: pyspark (==3.3.1)
